{
	"Id": "Lootable_00570",
	"IsStatic": true,
	"useGravity": true,
	"randomRotation": false,
	"Position": {
		"x": 0,
		"y": 0,
		"z": 0
	},
	"Rotation": {
		"x": 0,
		"y": 0,
		"z": 0
	},
	"IsGroupPosition": false,
	"GroupPositions": [],
	"Root": "5db5d067533aa77c477a6a72",
	"Items": [
		{
			"_id": "5db5d067533aa77c477a6a72",
			"_tpl": "5909d76c86f77471e53d2adf"
		},
		{
			"_id": "5db5d067533aa77c477a6a73",
			"_tpl": "544909bb4bdc2d6f028b4577",
			"parentId": "5db5d067533aa77c477a6a72",
			"slotId": "main",
			"location": {
				"x": 0,
				"y": 0,
				"r": 0
			}
		}
	]
}