{
	"Id": "Loot 135 (8)4336644",
	"IsStatic": false,
	"useGravity": true,
	"randomRotation": false,
	"Position": {
		"x": 184.323,
		"y": 6.351,
		"z": 183.421
	},
	"Rotation": {
		"x": 0.00000170754731,
		"y": 134.652985,
		"z": 0
	},
	"IsGroupPosition": false,
	"GroupPositions": [],
	"Root": "5d31e3d5645bb766be660a29",
	"Items": [
		{
			"_id": "5d31e3d5645bb766be660a29",
			"_tpl": "5c501a4d2e221602b412b540",
			"upd": {
				"FireMode": {
					"FireMode": "single"
				}
			}
		},
		{
			"_id": "5d31e3d5645bb766be660a2a",
			"_tpl": "5c5039be2e221602b177c9ff",
			"parentId": "5d31e3d5645bb766be660a29",
			"slotId": "mod_gas_block"
		},
		{
			"_id": "5d31e3d5645bb766be660a2b",
			"_tpl": "5c503d0a2e221602b542b7ef",
			"parentId": "5d31e3d5645bb766be660a29",
			"slotId": "mod_reciever"
		},
		{
			"_id": "5d31e3d5645bb766be660a2c",
			"_tpl": "5c503b1c2e221602b21d6e9d",
			"parentId": "5d31e3d5645bb766be660a29",
			"slotId": "mod_sight_rear"
		},
		{
			"_id": "5d31e3d5645bb766be660a2d",
			"_tpl": "5c503af12e221602b177ca02",
			"parentId": "5d31e3d5645bb766be660a29",
			"slotId": "mod_stock"
		},
		{
			"_id": "5d31e3d5645bb766be660a2e",
			"_tpl": "5c503ac82e221602b21d6e9a",
			"parentId": "5d31e3d5645bb766be660a29",
			"slotId": "mod_magazine"
		}
	]
}