{
	"Id": "loot_mix_food_med_ammo (22)3055704",
	"IsStatic": false,
	"useGravity": true,
	"randomRotation": true,
	"Position": {
		"x": -221.842,
		"y": 1.354,
		"z": -421.405
	},
	"Rotation": {
		"x": 0,
		"y": 0,
		"z": 0
	},
	"IsGroupPosition": false,
	"GroupPositions": [],
	"Root": "5db5d1908bcb9e33ce402675",
	"Items": [
		{
			"_id": "5db5d1908bcb9e33ce402675",
			"_tpl": "560d75f54bdc2da74d8b4573"
		},
		{
			"_id": "5db5d1908bcb9e33ce402676",
			"_tpl": "560d61e84bdc2da74d8b4571",
			"parentId": "5db5d1908bcb9e33ce402675",
			"slotId": "cartridges",
			"upd": {
				"StackObjectsCount": 30
			}
		}
	]
}