{
	"Id": "loot_mod (36)1329692",
	"IsStatic": false,
	"useGravity": true,
	"randomRotation": true,
	"Position": {
		"x": -268.83,
		"y": 4.24,
		"z": -316.496
	},
	"Rotation": {
		"x": 0,
		"y": 0,
		"z": 0
	},
	"IsGroupPosition": false,
	"GroupPositions": [],
	"Root": "5c8a662786f77422ab649a82",
	"Items": [
		{
			"_id": "5c8a662786f77422ab649a82",
			"_tpl": "5888988e24597752fe43a6fa"
		},
		{
			"_id": "5c8a662786f77422ab649a83",
			"_tpl": "5a6086ea4f39f99cd479502f",
			"parentId": "5c8a662786f77422ab649a82",
			"slotId": "cartridges",
			"upd": {
				"StackObjectsCount": 6
			}
		}
	]
}