{
	"Id": "loot_ammo_sup (41)3055110",
	"IsStatic": false,
	"useGravity": true,
	"randomRotation": true,
	"Position": {
		"x": -126.732,
		"y": 4.354,
		"z": -352.782
	},
	"Rotation": {
		"x": 0,
		"y": 0,
		"z": 0
	},
	"IsGroupPosition": false,
	"GroupPositions": [],
	"Root": "5db5d18ccd1e3d3a9450a43e",
	"Items": [
		{
			"_id": "5db5d18ccd1e3d3a9450a43e",
			"_tpl": "5c1127bdd174af44217ab8b9"
		},
		{
			"_id": "5db5d18ccd1e3d3a9450a43f",
			"_tpl": "5c0d56a986f774449d5de529",
			"parentId": "5db5d18ccd1e3d3a9450a43e",
			"slotId": "cartridges",
			"upd": {
				"StackObjectsCount": 20
			}
		}
	]
}