{
	"Id": "LootAmmoBoxes (8)4928948",
	"IsStatic": false,
	"useGravity": true,
	"randomRotation": false,
	"Position": {
		"x": -389.217,
		"y": 3.77000046,
		"z": 12.6189995
	},
	"Rotation": {
		"x": 0,
		"y": 0,
		"z": 0
	},
	"IsGroupPosition": false,
	"GroupPositions": [],
	"Root": "5d31e3df645bb73be0057fc1",
	"Items": [
		{
			"_id": "5d31e3df645bb73be0057fc1",
			"_tpl": "573722e82459776104581c21"
		},
		{
			"_id": "5d31e3df645bb73be0057fc2",
			"_tpl": "573718ba2459775a75491131",
			"parentId": "5d31e3df645bb73be0057fc1",
			"slotId": "cartridges",
			"upd": {
				"StackObjectsCount": 16
			}
		}
	]
}