{
	"Id": "loot_rf_ammo_true (37)6023722",
	"IsStatic": false,
	"useGravity": true,
	"randomRotation": true,
	"Position": {
		"x": -167.499634,
		"y": -2.37000036,
		"z": 32.9739075
	},
	"Rotation": {
		"x": 0,
		"y": 0,
		"z": 0
	},
	"IsGroupPosition": false,
	"GroupPositions": [],
	"Root": "5e0676070b8cde1bad722ac2",
	"Items": [
		{
			"_id": "5e0676070b8cde1bad722ac2",
			"_tpl": "57372fc52459776998772ca1"
		},
		{
			"_id": "5e0676070b8cde1bad722ac3",
			"_tpl": "56dff4ecd2720b5f5a8b4568",
			"parentId": "5e0676070b8cde1bad722ac2",
			"slotId": "cartridges",
			"upd": {
				"StackObjectsCount": 60
			}
		},
		{
			"_id": "5e0676070b8cde1bad722ac4",
			"_tpl": "56dff4ecd2720b5f5a8b4568",
			"parentId": "5e0676070b8cde1bad722ac2",
			"slotId": "cartridges",
			"location": 1,
			"upd": {
				"StackObjectsCount": 60
			}
		}
	]
}