{
	"Id": "loot_rf_ammo_true (76)642002",
	"IsStatic": false,
	"useGravity": true,
	"randomRotation": true,
	"Position": {
		"x": 91.98901,
		"y": -5.678,
		"z": -153.405
	},
	"Rotation": {
		"x": 0,
		"y": 0,
		"z": 0
	},
	"IsGroupPosition": false,
	"GroupPositions": [],
	"Root": "5db5d02609aff62a3d371b20",
	"Items": [
		{
			"_id": "5db5d02609aff62a3d371b20",
			"_tpl": "57372deb245977685d4159b3"
		},
		{
			"_id": "5db5d02609aff62a3d371b21",
			"_tpl": "56dff338d2720bbd668b4569",
			"parentId": "5db5d02609aff62a3d371b20",
			"slotId": "cartridges",
			"upd": {
				"StackObjectsCount": 60
			}
		},
		{
			"_id": "5db5d02609aff62a3d371b22",
			"_tpl": "56dff338d2720bbd668b4569",
			"parentId": "5db5d02609aff62a3d371b20",
			"slotId": "cartridges",
			"location": 1,
			"upd": {
				"StackObjectsCount": 60
			}
		}
	]
}