{
	"Id": "loot_ammo_regular (4)666622",
	"IsStatic": false,
	"useGravity": true,
	"randomRotation": true,
	"Position": {
		"x": 88.1247559,
		"y": 0.08999634,
		"z": -31.4907532
	},
	"Rotation": {
		"x": 0,
		"y": 0,
		"z": 0
	},
	"IsGroupPosition": false,
	"GroupPositions": [],
	"Root": "5dd2961886f774793f5f966b",
	"Items": [
		{
			"_id": "5dd2961886f774793f5f966b",
			"_tpl": "5b7bef1e5acfc43d82528402"
		},
		{
			"_id": "5dd2961886f774793f5f966c",
			"_tpl": "5a6086ea4f39f99cd479502f",
			"parentId": "5dd2961886f774793f5f966b",
			"slotId": "cartridges",
			"upd": {
				"StackObjectsCount": 7
			}
		}
	]
}