{
	"Id": "loot_rf_ammo_true (48)673272",
	"IsStatic": false,
	"useGravity": true,
	"randomRotation": true,
	"Position": {
		"x": -167.845276,
		"y": 3.13300037,
		"z": 33.11258
	},
	"Rotation": {
		"x": 0,
		"y": 0,
		"z": 0
	},
	"IsGroupPosition": false,
	"GroupPositions": [],
	"Root": "5dd2961d86f77414f52bc35b",
	"Items": [
		{
			"_id": "5dd2961d86f77414f52bc35b",
			"_tpl": "57372e4a24597768553071c2"
		},
		{
			"_id": "5dd2961d86f77414f52bc35c",
			"_tpl": "56dff338d2720bbd668b4569",
			"parentId": "5dd2961d86f77414f52bc35b",
			"slotId": "cartridges",
			"upd": {
				"StackObjectsCount": 30
			}
		}
	]
}