{
	"Id": "loot_mix_food_med_ammo (139)618468",
	"IsStatic": false,
	"useGravity": true,
	"randomRotation": true,
	"Position": {
		"x": 198.440979,
		"y": -5.732,
		"z": -11.2939758
	},
	"Rotation": {
		"x": 0,
		"y": 0,
		"z": 0
	},
	"IsGroupPosition": false,
	"GroupPositions": [],
	"Root": "5db5d07dcd1e3d3a945096bf",
	"Items": [
		{
			"_id": "5db5d07dcd1e3d3a945096bf",
			"_tpl": "57372e4a24597768553071c2"
		},
		{
			"_id": "5db5d07dcd1e3d3a945096c0",
			"_tpl": "56dff338d2720bbd668b4569",
			"parentId": "5db5d07dcd1e3d3a945096bf",
			"slotId": "cartridges",
			"upd": {
				"StackObjectsCount": 30
			}
		}
	]
}