{
	"Id": "Lootable_00387",
	"IsStatic": true,
	"useGravity": true,
	"randomRotation": false,
	"Position": {
		"x": 0,
		"y": 0,
		"z": 0
	},
	"Rotation": {
		"x": 0,
		"y": 0,
		"z": 0
	},
	"IsGroupPosition": false,
	"GroupPositions": [],
	"Root": "5dd2961f86f774794047ca5b",
	"Items": [
		{
			"_id": "5dd2961f86f774794047ca5b",
			"_tpl": "5909d36d86f774660f0bb900"
		},
		{
			"_id": "5dd2961f86f774794047ca5c",
			"_tpl": "5710c24ad2720bc3458b45a3",
			"parentId": "5dd2961f86f774794047ca5b",
			"slotId": "main",
			"location": {
				"x": 0,
				"y": 0,
				"r": 0
			}
		}
	]
}