{
	"Id": "Lootable_00010",
	"IsStatic": true,
	"useGravity": true,
	"randomRotation": false,
	"Position": {
		"x": 0,
		"y": 0,
		"z": 0
	},
	"Rotation": {
		"x": 0,
		"y": 0,
		"z": 0
	},
	"IsGroupPosition": false,
	"GroupPositions": [],
	"Root": "5e06760a0b8cde1bad722dcd",
	"Items": [
		{
			"_id": "5e06760a0b8cde1bad722dcd",
			"_tpl": "5909d5ef86f77467974efbd8"
		},
		{
			"_id": "5e06760a0b8cde1bad722dce",
			"_tpl": "57ffb0062459777a045af529",
			"parentId": "5e06760a0b8cde1bad722dcd",
			"slotId": "main",
			"location": {
				"x": 0,
				"y": 0,
				"r": 0
			}
		}
	]
}