{
	"Id": "loot_rf_ammo_true (88)669996",
	"IsStatic": false,
	"useGravity": true,
	"randomRotation": true,
	"Position": {
		"x": -103.810242,
		"y": 6.20900059,
		"z": 97.6886
	},
	"Rotation": {
		"x": 0,
		"y": 0,
		"z": 0
	},
	"IsGroupPosition": false,
	"GroupPositions": [],
	"Root": "5dd2961386f774793d4cd67c",
	"Items": [
		{
			"_id": "5dd2961386f774793d4cd67c",
			"_tpl": "560d75f54bdc2da74d8b4573"
		},
		{
			"_id": "5dd2961386f774793d4cd67d",
			"_tpl": "560d61e84bdc2da74d8b4571",
			"parentId": "5dd2961386f774793d4cd67c",
			"slotId": "cartridges",
			"upd": {
				"StackObjectsCount": 30
			}
		}
	]
}