{
	"Id": "Lootable_00428",
	"IsStatic": true,
	"useGravity": true,
	"randomRotation": false,
	"Position": {
		"x": 0,
		"y": 0,
		"z": 0
	},
	"Rotation": {
		"x": 0,
		"y": 0,
		"z": 0
	},
	"IsGroupPosition": false,
	"GroupPositions": [],
	"Root": "5db5d0731d9e8a753205a494",
	"Items": [
		{
			"_id": "5db5d0731d9e8a753205a494",
			"_tpl": "578f87a3245977356274f2cb"
		},
		{
			"_id": "5db5d0731d9e8a753205a495",
			"_tpl": "544fb62a4bdc2dfb738b4568",
			"parentId": "5db5d0731d9e8a753205a494",
			"slotId": "main",
			"location": {
				"x": 0,
				"y": 0,
				"r": 0
			}
		}
	]
}