{
	"Id": "loot_rf_ammo_true (16)725686",
	"IsStatic": false,
	"useGravity": true,
	"randomRotation": true,
	"Position": {
		"x": -60.3049927,
		"y": -6.19000244,
		"z": -32.2349854
	},
	"Rotation": {
		"x": 0,
		"y": 0,
		"z": 0
	},
	"IsGroupPosition": false,
	"GroupPositions": [],
	"Root": "5dd2961386f7740728172e21",
	"Items": [
		{
			"_id": "5dd2961386f7740728172e21",
			"_tpl": "573727c624597765cc785b5b"
		},
		{
			"_id": "5dd2961386f7740728172e22",
			"_tpl": "5737201124597760fc4431f1",
			"parentId": "5dd2961386f7740728172e21",
			"slotId": "cartridges",
			"upd": {
				"StackObjectsCount": 16
			}
		}
	]
}