{
	"Id": "Lootable_00567",
	"IsStatic": true,
	"useGravity": true,
	"randomRotation": false,
	"Position": {
		"x": 0,
		"y": 0,
		"z": 0
	},
	"Rotation": {
		"x": 0,
		"y": 0,
		"z": 0
	},
	"IsGroupPosition": false,
	"GroupPositions": [],
	"Root": "5e06760926f42d2de9400499",
	"Items": [
		{
			"_id": "5e06760926f42d2de9400499",
			"_tpl": "5909d36d86f774660f0bb900"
		},
		{
			"_id": "5e06760926f42d2de940049a",
			"_tpl": "5a2a57cfc4a2826c6e06d44a",
			"parentId": "5e06760926f42d2de9400499",
			"slotId": "main",
			"location": {
				"x": 0,
				"y": 0,
				"r": 0
			}
		}
	]
}