{
	"Id": "loot_mod_common (37)5974434",
	"IsStatic": false,
	"useGravity": true,
	"randomRotation": true,
	"Position": {
		"x": -12.1129761,
		"y": -4.113,
		"z": -89.1429749
	},
	"Rotation": {
		"x": 0,
		"y": 0,
		"z": 0
	},
	"IsGroupPosition": false,
	"GroupPositions": [],
	"Root": "5e06760d8b77ae7722639225",
	"Items": [
		{
			"_id": "5e06760d8b77ae7722639225",
			"_tpl": "5cfe8010d7ad1a59283b14c6"
		},
		{
			"_id": "5e06760d8b77ae7722639226",
			"_tpl": "59e655cb86f77411dc52a77b",
			"parentId": "5e06760d8b77ae7722639225",
			"slotId": "cartridges",
			"upd": {
				"StackObjectsCount": 5
			}
		}
	]
}