{
	"Id": "loot_rf_ammo_true (160)672844",
	"IsStatic": false,
	"useGravity": true,
	"randomRotation": true,
	"Position": {
		"x": 24.9979858,
		"y": -5.795,
		"z": -175.90799
	},
	"Rotation": {
		"x": 0,
		"y": 0,
		"z": 0
	},
	"IsGroupPosition": false,
	"GroupPositions": [],
	"Root": "5dd2961386f774793d4cd5b3",
	"Items": [
		{
			"_id": "5dd2961386f774793d4cd5b3",
			"_tpl": "57372c21245977670937c6c2"
		},
		{
			"_id": "5dd2961386f774793d4cd5b4",
			"_tpl": "56dff061d2720bb5668b4567",
			"parentId": "5dd2961386f774793d4cd5b3",
			"slotId": "cartridges",
			"upd": {
				"StackObjectsCount": 60
			}
		},
		{
			"_id": "5dd2961386f774793d4cd5b5",
			"_tpl": "56dff061d2720bb5668b4567",
			"parentId": "5dd2961386f774793d4cd5b3",
			"slotId": "cartridges",
			"location": 1,
			"upd": {
				"StackObjectsCount": 60
			}
		}
	]
}