{
	"Id": "loot_rf_ammo_true (34)722620",
	"IsStatic": false,
	"useGravity": true,
	"randomRotation": true,
	"Position": {
		"x": -159.898682,
		"y": 6.095,
		"z": 52.60791
	},
	"Rotation": {
		"x": 0,
		"y": 0,
		"z": 0
	},
	"IsGroupPosition": false,
	"GroupPositions": [],
	"Root": "5dd2961386f7740728172e79",
	"Items": [
		{
			"_id": "5dd2961386f7740728172e79",
			"_tpl": "57372c89245977685d4159b1"
		},
		{
			"_id": "5dd2961386f7740728172e7a",
			"_tpl": "56dff061d2720bb5668b4567",
			"parentId": "5dd2961386f7740728172e79",
			"slotId": "cartridges",
			"upd": {
				"StackObjectsCount": 30
			}
		}
	]
}