{
	"Id": "loot_mix_food_med_ammo (28)2175564",
	"IsStatic": false,
	"useGravity": true,
	"randomRotation": true,
	"Position": {
		"x": -165.164978,
		"y": 0.2676015,
		"z": 41.0939941
	},
	"Rotation": {
		"x": 0,
		"y": 0,
		"z": 0
	},
	"IsGroupPosition": false,
	"GroupPositions": [],
	"Root": "5d7227ac5549dd27ff02771a",
	"Items": [
		{
			"_id": "5d7227ac5549dd27ff02771a",
			"_tpl": "573728cc24597765cc785b5d"
		},
		{
			"_id": "5d7227ac5549dd27ff02771b",
			"_tpl": "57372140245977611f70ee91",
			"parentId": "5d7227ac5549dd27ff02771a",
			"slotId": "cartridges",
			"upd": {
				"StackObjectsCount": 16
			}
		}
	]
}