{
	"Id": "loot_mod_true (57)678714",
	"IsStatic": false,
	"useGravity": true,
	"randomRotation": true,
	"Position": {
		"x": 235.600952,
		"y": -1.557,
		"z": -101.539
	},
	"Rotation": {
		"x": 0,
		"y": 0,
		"z": 0
	},
	"IsGroupPosition": false,
	"GroupPositions": [],
	"Root": "5dd2961d86f774794047c61b",
	"Items": [
		{
			"_id": "5dd2961d86f774794047c61b",
			"_tpl": "5bed61680db834001d2c45ab"
		},
		{
			"_id": "5dd2961d86f774794047c61c",
			"_tpl": "56dff216d2720bbd668b4568",
			"parentId": "5dd2961d86f774794047c61b",
			"slotId": "cartridges",
			"upd": {
				"StackObjectsCount": 1
			}
		}
	]
}