{
	"Id": "loot_mod_true (6)6004924",
	"IsStatic": false,
	"useGravity": true,
	"randomRotation": true,
	"Position": {
		"x": -163.19,
		"y": -8.0354,
		"z": 69.73999
	},
	"Rotation": {
		"x": 0,
		"y": 0,
		"z": 0
	},
	"IsGroupPosition": false,
	"GroupPositions": [],
	"Root": "5e06760e9a5d683c327edbee",
	"Items": [
		{
			"_id": "5e06760e9a5d683c327edbee",
			"_tpl": "55d480c04bdc2d1d4e8b456a"
		},
		{
			"_id": "5e06760e9a5d683c327edbef",
			"_tpl": "56dfef82d2720bbd668b4567",
			"parentId": "5e06760e9a5d683c327edbee",
			"slotId": "cartridges",
			"upd": {
				"StackObjectsCount": 26
			}
		}
	]
}