{
	"Id": "loot_ammo_rus (1)5973760",
	"IsStatic": false,
	"useGravity": true,
	"randomRotation": true,
	"Position": {
		"x": 8.437561,
		"y": -5.915001,
		"z": -14.0195618
	},
	"Rotation": {
		"x": 0,
		"y": 0,
		"z": 0
	},
	"IsGroupPosition": false,
	"GroupPositions": [],
	"Root": "5e06761396074431445d4a66",
	"Items": [
		{
			"_id": "5e06761396074431445d4a66",
			"_tpl": "5737256c2459776125652acd"
		},
		{
			"_id": "5e06761396074431445d4a67",
			"_tpl": "57371aab2459775a77142f22",
			"parentId": "5e06761396074431445d4a66",
			"slotId": "cartridges",
			"upd": {
				"StackObjectsCount": 16
			}
		}
	]
}