{
	"Id": "loot_rf_ammo_true (134)638252",
	"IsStatic": false,
	"useGravity": true,
	"randomRotation": true,
	"Position": {
		"x": -103.995972,
		"y": -3.141,
		"z": -154.993988
	},
	"Rotation": {
		"x": 0,
		"y": 0,
		"z": 0
	},
	"IsGroupPosition": false,
	"GroupPositions": [],
	"Root": "5db5d02609aff62a3d371a23",
	"Items": [
		{
			"_id": "5db5d02609aff62a3d371a23",
			"_tpl": "573727c624597765cc785b5b"
		},
		{
			"_id": "5db5d02609aff62a3d371a24",
			"_tpl": "5737201124597760fc4431f1",
			"parentId": "5db5d02609aff62a3d371a23",
			"slotId": "cartridges",
			"upd": {
				"StackObjectsCount": 16
			}
		}
	]
}