{
	"Id": "loot_rf_ammo_true (54)5982536",
	"IsStatic": false,
	"useGravity": true,
	"randomRotation": true,
	"Position": {
		"x": -29.0390015,
		"y": -5.875,
		"z": -23.1269836
	},
	"Rotation": {
		"x": 0,
		"y": 0,
		"z": 0
	},
	"IsGroupPosition": false,
	"GroupPositions": [],
	"Root": "5e06760d8b77ae7722639385",
	"Items": [
		{
			"_id": "5e06760d8b77ae7722639385",
			"_tpl": "57372c89245977685d4159b1"
		},
		{
			"_id": "5e06760d8b77ae7722639386",
			"_tpl": "56dff061d2720bb5668b4567",
			"parentId": "5e06760d8b77ae7722639385",
			"slotId": "cartridges",
			"upd": {
				"StackObjectsCount": 30
			}
		}
	]
}