{
	"Id": "loot_rf_ammo_true (59)5985894",
	"IsStatic": false,
	"useGravity": true,
	"randomRotation": true,
	"Position": {
		"x": -119.035278,
		"y": -2.27399969,
		"z": 97.55359
	},
	"Rotation": {
		"x": 0,
		"y": 0,
		"z": 0
	},
	"IsGroupPosition": false,
	"GroupPositions": [],
	"Root": "5e06761396074431445d4cdb",
	"Items": [
		{
			"_id": "5e06761396074431445d4cdb",
			"_tpl": "573722e82459776104581c21"
		},
		{
			"_id": "5e06761396074431445d4cdc",
			"_tpl": "573718ba2459775a75491131",
			"parentId": "5e06761396074431445d4cdb",
			"slotId": "cartridges",
			"upd": {
				"StackObjectsCount": 16
			}
		}
	]
}