{
	"Id": "loot_rf_ammo_true (37)6013866",
	"IsStatic": false,
	"useGravity": true,
	"randomRotation": true,
	"Position": {
		"x": -125.650269,
		"y": 3.1420002,
		"z": 91.5426
	},
	"Rotation": {
		"x": 0,
		"y": 0,
		"z": 0
	},
	"IsGroupPosition": false,
	"GroupPositions": [],
	"Root": "5e0676070b8cde1bad722ac0",
	"Items": [
		{
			"_id": "5e0676070b8cde1bad722ac0",
			"_tpl": "57372e4a24597768553071c2"
		},
		{
			"_id": "5e0676070b8cde1bad722ac1",
			"_tpl": "56dff338d2720bbd668b4569",
			"parentId": "5e0676070b8cde1bad722ac0",
			"slotId": "cartridges",
			"upd": {
				"StackObjectsCount": 30
			}
		}
	]
}