{
	"Id": "loot_rf_ammo_true (156)675504",
	"IsStatic": false,
	"useGravity": true,
	"randomRotation": true,
	"Position": {
		"x": -260.254028,
		"y": -10.469,
		"z": -67.431
	},
	"Rotation": {
		"x": 0,
		"y": 0,
		"z": 0
	},
	"IsGroupPosition": false,
	"GroupPositions": [],
	"Root": "5dd2961d86f774794047c6ea",
	"Items": [
		{
			"_id": "5dd2961d86f774794047c6ea",
			"_tpl": "5737250c2459776125652acc"
		},
		{
			"_id": "5dd2961d86f774794047c6eb",
			"_tpl": "573719df2459775a626ccbc2",
			"parentId": "5dd2961d86f774794047c6ea",
			"slotId": "cartridges",
			"upd": {
				"StackObjectsCount": 16
			}
		}
	]
}