{
	"Id": "loot_rf_ammo_true (121)594480",
	"IsStatic": false,
	"useGravity": true,
	"randomRotation": true,
	"Position": {
		"x": -66.13483,
		"y": -9.752577,
		"z": 25.5752869
	},
	"Rotation": {
		"x": 0,
		"y": 0,
		"z": 0
	},
	"IsGroupPosition": false,
	"GroupPositions": [],
	"Root": "5db5d0701d9e8a753205a1df",
	"Items": [
		{
			"_id": "5db5d0701d9e8a753205a1df",
			"_tpl": "57372c89245977685d4159b1"
		},
		{
			"_id": "5db5d0701d9e8a753205a1e0",
			"_tpl": "56dff061d2720bb5668b4567",
			"parentId": "5db5d0701d9e8a753205a1df",
			"slotId": "cartridges",
			"upd": {
				"StackObjectsCount": 30
			}
		}
	]
}