{
	"Id": "loot_rf_ammo_true (71)696184",
	"IsStatic": false,
	"useGravity": true,
	"randomRotation": true,
	"Position": {
		"x": -104.821289,
		"y": -0.305999756,
		"z": 95.0376
	},
	"Rotation": {
		"x": 0,
		"y": 0,
		"z": 0
	},
	"IsGroupPosition": false,
	"GroupPositions": [],
	"Root": "5dd2961d86f774794047c7ce",
	"Items": [
		{
			"_id": "5dd2961d86f774794047c7ce",
			"_tpl": "57372c89245977685d4159b1"
		},
		{
			"_id": "5dd2961d86f774794047c7cf",
			"_tpl": "56dff061d2720bb5668b4567",
			"parentId": "5dd2961d86f774794047c7ce",
			"slotId": "cartridges",
			"upd": {
				"StackObjectsCount": 30
			}
		}
	]
}