{
	"Id": "Lootable_00187",
	"IsStatic": true,
	"useGravity": true,
	"randomRotation": false,
	"Position": {
		"x": 0,
		"y": 0,
		"z": 0
	},
	"Rotation": {
		"x": 0,
		"y": 0,
		"z": 0
	},
	"IsGroupPosition": false,
	"GroupPositions": [],
	"Root": "5db5d04ecd1e3d3a9450844c",
	"Items": [
		{
			"_id": "5db5d04ecd1e3d3a9450844c",
			"_tpl": "578f87b7245977356274f2cd"
		},
		{
			"_id": "5db5d04ecd1e3d3a9450844d",
			"_tpl": "590a3c0a86f774385a33c450",
			"parentId": "5db5d04ecd1e3d3a9450844c",
			"slotId": "main",
			"location": {
				"x": 0,
				"y": 0,
				"r": 0
			}
		}
	]
}