{
	"Id": "LootFood[5] (47)4381696",
	"IsStatic": false,
	"useGravity": true,
	"randomRotation": false,
	"Position": {
		"x": -181.342041,
		"y": -0.33,
		"z": -77.836
	},
	"Rotation": {
		"x": 0,
		"y": 0,
		"z": 0
	},
	"IsGroupPosition": false,
	"GroupPositions": [],
	"Root": "5db5d067f113b904523ad759",
	"Items": [
		{
			"_id": "5db5d067f113b904523ad759",
			"_tpl": "55802d5f4bdc2dac148b458e"
		},
		{
			"_id": "5db5d067f113b904523ad75a",
			"_tpl": "59e6906286f7746c9f75e847",
			"parentId": "5db5d067f113b904523ad759",
			"slotId": "cartridges",
			"upd": {
				"StackObjectsCount": 15
			}
		}
	]
}