{
	"Id": "GunsafeSpawn 1 (7)(Clone)4379984",
	"IsStatic": false,
	"useGravity": true,
	"randomRotation": false,
	"Position": {
		"x": -201.496048,
		"y": -3.39111781,
		"z": -81.319664
	},
	"Rotation": {
		"x": 270,
		"y": 212.779739,
		"z": 0
	},
	"IsGroupPosition": false,
	"GroupPositions": [],
	"Root": "5db5d0778bcb9e33ce400caf",
	"Items": [
		{
			"_id": "5db5d0778bcb9e33ce400caf",
			"_tpl": "587df583245977373c4f1129"
		},
		{
			"_id": "5db5d0778bcb9e33ce400cb0",
			"_tpl": "59e655cb86f77411dc52a77b",
			"parentId": "5db5d0778bcb9e33ce400caf",
			"slotId": "cartridges",
			"upd": {
				"StackObjectsCount": 2
			}
		}
	]
}